tunnelproxy/__init__.py
tunnelproxy/__main__.py
tunnelproxy/_adapter.py
tunnelproxy/_config.py
tunnelproxy/_proxy.py
tunnelproxy/_version.py
tunnelproxy-0.2.1.dist-info/LICENSE
tunnelproxy-0.2.1.dist-info/METADATA
tunnelproxy-0.2.1.dist-info/WHEEL
tunnelproxy-0.2.1.dist-info/top_level.txt
tunnelproxy-0.2.1.dist-info/RECORD
