Metadata-Version: 2.1
Name: tunnelproxy
Version: 0.2.1
Summary: A small whitelisting HTTP CONNECT proxy
Home-page: https://github.com/De117/tunnelproxy
Author: Antun Maldini
Author-email: antun.maldini@gmail.com
License: MIT
Project-URL: Source, https://github.com/De117/tunnelproxy
Project-URL: Tracker, https://github.com/De117/tunnelproxy/issues
Project-URL: Changelog, https://github.com/De117/tunnelproxy/blob/master/docs/CHANGELOG.md
Keywords: whitelist proxy HTTP
Classifier: Development Status :: 3 - Alpha
Classifier: Framework :: Trio
Classifier: Intended Audience :: Developers
Classifier: Intended Audience :: System Administrators
Classifier: License :: OSI Approved :: MIT License
Classifier: Operating System :: POSIX
Classifier: Programming Language :: Python :: 3 :: Only
Classifier: Programming Language :: Python :: 3.9
Classifier: Programming Language :: Python :: 3.10
Classifier: Programming Language :: Python :: 3.11
Classifier: Programming Language :: Python :: 3.12
Classifier: Programming Language :: Python :: 3.13
Classifier: Programming Language :: Python :: Implementation :: CPython
Classifier: Programming Language :: Python :: Implementation :: PyPy
Classifier: Topic :: Internet :: Proxy Servers
Classifier: Topic :: Internet :: WWW/HTTP :: HTTP Servers
Classifier: Topic :: Security
Classifier: Topic :: System :: Networking
Requires-Python: >=3.9
License-File: LICENSE
Requires-Dist: trio <0.31,>=0.24
Requires-Dist: h11 ~=0.14.0
